tslumd/__init__.py
tslumd/common.py
tslumd/messages.py
tslumd/receiver.py
tslumd/sender.py
tslumd/tallyobj.py
tslumd/utils.py
tslumd-0.0.7.dist-info/licenses/LICENSE
tslumd-0.0.7.dist-info/METADATA
tslumd-0.0.7.dist-info/WHEEL
tslumd-0.0.7.dist-info/top_level.txt
tslumd-0.0.7.dist-info/RECORD
