Metadata-Version: 2.4
Name: tslumd
Version: 0.0.7
Summary: Client and Server for TSLUMD Tally Protocols
Home-page: https://github.com/nocarryr/tslumd
Author: Matthew Reid
Author-email: matt@nomadic-recording.com
License: MIT
Platform: any
Classifier: Development Status :: 2 - Pre-Alpha
Classifier: Natural Language :: English
Classifier: Operating System :: OS Independent
Classifier: Programming Language :: Python :: 3
Classifier: Programming Language :: Python :: 3.8
Classifier: Programming Language :: Python :: 3.9
Classifier: Programming Language :: Python :: 3.10
Classifier: Programming Language :: Python :: 3.11
Classifier: Programming Language :: Python :: 3.12
Classifier: Programming Language :: Python :: 3.13
Classifier: Intended Audience :: Developers
Classifier: Intended Audience :: Information Technology
Classifier: Framework :: AsyncIO
Classifier: Topic :: Multimedia :: Video
Classifier: Topic :: Software Development :: Libraries
Classifier: Topic :: Software Development :: Libraries :: Python Modules
License-File: LICENSE
Requires-Dist: python-dispatch
Requires-Dist: importlib_metadata; python_version < "3.8"
Dynamic: license-file
